MANIFEST.in
README.txt
setup.py
docs/HISTORY.txt
docs/INSTALL.txt
docs/LICENSE.GPL
docs/LICENSE.txt
zettwerk/__init__.py
zettwerk.fullcalendar.egg-info/PKG-INFO
zettwerk.fullcalendar.egg-info/SOURCES.txt
zettwerk.fullcalendar.egg-info/dependency_links.txt
zettwerk.fullcalendar.egg-info/entry_points.txt
zettwerk.fullcalendar.egg-info/namespace_packages.txt
zettwerk.fullcalendar.egg-info/not-zip-safe
zettwerk.fullcalendar.egg-info/requires.txt
zettwerk.fullcalendar.egg-info/top_level.txt
zettwerk/fullcalendar/README.txt
zettwerk/fullcalendar/__init__.py
zettwerk/fullcalendar/config.py
zettwerk/fullcalendar/configure.zcml
zettwerk/fullcalendar/browser/__init__.py
zettwerk/fullcalendar/browser/calendar_preview_view.pt
zettwerk/fullcalendar/browser/calendar_preview_view.py
zettwerk/fullcalendar/browser/calendarview.pt
zettwerk/fullcalendar/browser/calendarview.py
zettwerk/fullcalendar/browser/configure.zcml
zettwerk/fullcalendar/browser/eventsview.py
zettwerk/fullcalendar/browser/fullcalendar/fullcalendar.css
zettwerk/fullcalendar/browser/fullcalendar/fullcalendar.js
zettwerk/fullcalendar/browser/fullcalendar/fullcalendar.min.js
zettwerk/fullcalendar/browser/fullcalendar/fullcalendar.print.css
zettwerk/fullcalendar/browser/fullcalendar/gcal.js
zettwerk/fullcalendar/browser/javascript/enable.js
zettwerk/fullcalendar/browser/stylesheets/zettwerk.fullcalendar.css
zettwerk/fullcalendar/i18n/plone-de.po
zettwerk/fullcalendar/i18n/plone-en.po
zettwerk/fullcalendar/i18n/plone-fi.po
zettwerk/fullcalendar/locales/zettwerk.fullcalendar.pot
zettwerk/fullcalendar/locales/bg/LC_MESSAGES/zettwerk.fullcalendar.po
zettwerk/fullcalendar/locales/da/LC_MESSAGES/zettwerk.fullcalendar.po
zettwerk/fullcalendar/locales/de/LC_MESSAGES/README.txt
zettwerk/fullcalendar/locales/de/LC_MESSAGES/zettwerk.fullcalendar.po
zettwerk/fullcalendar/locales/en/LC_MESSAGES/README.txt
zettwerk/fullcalendar/locales/en/LC_MESSAGES/zettwerk.fullcalendar.po
zettwerk/fullcalendar/locales/fi/LC_MESSAGES/zettwerk.fullcalendar.po
zettwerk/fullcalendar/profiles/default/cssregistry.xml
zettwerk/fullcalendar/profiles/default/jsregistry.xml
zettwerk/fullcalendar/profiles/default/metadata.xml
zettwerk/fullcalendar/profiles/default/types/Folder.xml
zettwerk/fullcalendar/profiles/default/types/Topic.xml
zettwerk/fullcalendar/tests/__init__.py
zettwerk/fullcalendar/tests/base.py
