Metadata-Version: 1.1
Name: zettwerk.fullcalendar
Version: 0.3.1
Summary: Adding jquery.fullcalendar to plone 4
Home-page: http://svn.plone.org/svn/collective/zettwerk.fullcalendar
Author: zettwerk GmbH
Author-email: jk@zettwerk.com
License: GPL
Keywords: plone,view,calendar,fullcalendar
Platform: UNKNOWN
Classifier: Framework :: Plone
Classifier: Programming Language :: Python
